{
    "description": "",
    "tags": [],
    "size": {
        "height": 4032,
        "width": 3024
    },
    "objects": [
        {
            "id": 14424070,
            "classId": 20791,
            "description": "",
            "geometryType": "polygon",
            "labelerLogin": "gr@datasetninja.com",
            "createdAt": "2023-07-11T11:57:34.895Z",
            "updatedAt": "2023-07-11T11:57:34.895Z",
            "tags": [],
            "classTitle": "b_green",
            "points": {
                "exterior": [
                    [
                        2219,
                        1937
                    ],
                    [
                        2181,
                        2019
                    ],
                    [
                        2162,
                        2111
                    ],
                    [
                        2174,
                        2205
                    ],
                    [
                        2205,
                        2266
                    ],
                    [
                        2270,
                        2317
                    ],
                    [
                        2322,
                        2338
                    ],
                    [
                        2310,
                        2270
                    ],
                    [
                        2324,
                        2202
                    ],
                    [
                        2360,
                        2137
                    ],
                    [
                        2456,
                        2066
                    ],
                    [
                        2620,
                        2059
                    ],
                    [
                        2681,
                        2108
                    ],
                    [
                        2754,
                        2167
                    ],
                    [
                        2763,
                        2113
                    ],
                    [
                        2747,
                        2017
                    ],
                    [
                        2721,
                        1960
                    ],
                    [
                        2637,
                        1876
                    ],
                    [
                        2590,
                        1845
                    ],
                    [
                        2489,
                        1824
                    ],
                    [
                        2392,
                        1838
                    ],
                    [
                        2263,
                        1897
                    ]
                ],
                "interior": []
            }
        },
        {
            "id": 14424069,
            "classId": 20791,
            "description": "",
            "geometryType": "polygon",
            "labelerLogin": "gr@datasetninja.com",
            "createdAt": "2023-07-11T11:57:34.894Z",
            "updatedAt": "2023-07-11T11:57:34.894Z",
            "tags": [],
            "classTitle": "b_green",
            "points": {
                "exterior": [
                    [
                        2763,
                        2188
                    ],
                    [
                        2787,
                        2322
                    ],
                    [
                        2735,
                        2475
                    ],
                    [
                        2688,
                        2529
                    ],
                    [
                        2634,
                        2554
                    ],
                    [
                        2573,
                        2562
                    ],
                    [
                        2500,
                        2550
                    ],
                    [
                        2437,
                        2515
                    ],
                    [
                        2374,
                        2458
                    ],
                    [
                        2329,
                        2388
                    ],
                    [
                        2320,
                        2341
                    ],
                    [
                        2310,
                        2270
                    ],
                    [
                        2329,
                        2198
                    ],
                    [
                        2362,
                        2141
                    ],
                    [
                        2456,
                        2061
                    ],
                    [
                        2620,
                        2054
                    ],
                    [
                        2681,
                        2108
                    ],
                    [
                        2759,
                        2167
                    ]
                ],
                "interior": []
            }
        },
        {
            "id": 14424068,
            "classId": 20790,
            "description": "",
            "geometryType": "polygon",
            "labelerLogin": "gr@datasetninja.com",
            "createdAt": "2023-07-11T11:57:34.894Z",
            "updatedAt": "2023-07-11T11:57:34.894Z",
            "tags": [],
            "classTitle": "b_half_ripened",
            "points": {
                "exterior": [
                    [
                        1658,
                        2594
                    ],
                    [
                        1719,
                        2648
                    ],
                    [
                        1740,
                        2716
                    ],
                    [
                        1758,
                        2827
                    ],
                    [
                        1749,
                        2867
                    ],
                    [
                        1714,
                        2942
                    ],
                    [
                        1702,
                        2982
                    ],
                    [
                        1679,
                        3005
                    ],
                    [
                        1580,
                        3036
                    ],
                    [
                        1505,
                        3045
                    ],
                    [
                        1432,
                        3003
                    ],
                    [
                        1388,
                        2942
                    ],
                    [
                        1341,
                        2869
                    ],
                    [
                        1317,
                        2792
                    ],
                    [
                        1324,
                        2740
                    ],
                    [
                        1329,
                        2702
                    ],
                    [
                        1376,
                        2616
                    ],
                    [
                        1442,
                        2576
                    ],
                    [
                        1503,
                        2554
                    ],
                    [
                        1559,
                        2557
                    ],
                    [
                        1620,
                        2576
                    ]
                ],
                "interior": []
            }
        },
        {
            "id": 14424067,
            "classId": 20791,
            "description": "",
            "geometryType": "polygon",
            "labelerLogin": "gr@datasetninja.com",
            "createdAt": "2023-07-11T11:57:34.893Z",
            "updatedAt": "2023-07-11T11:57:34.893Z",
            "tags": [],
            "classTitle": "b_green",
            "points": {
                "exterior": [
                    [
                        1052,
                        2662
                    ],
                    [
                        993,
                        2709
                    ],
                    [
                        958,
                        2754
                    ],
                    [
                        946,
                        2813
                    ],
                    [
                        944,
                        2895
                    ],
                    [
                        979,
                        2989
                    ],
                    [
                        1061,
                        3048
                    ],
                    [
                        1188,
                        3024
                    ],
                    [
                        1240,
                        2970
                    ],
                    [
                        1265,
                        2876
                    ],
                    [
                        1265,
                        2796
                    ],
                    [
                        1263,
                        2731
                    ],
                    [
                        1202,
                        2670
                    ],
                    [
                        1164,
                        2653
                    ],
                    [
                        1080,
                        2653
                    ]
                ],
                "interior": []
            }
        },
        {
            "id": 14424066,
            "classId": 20791,
            "description": "",
            "geometryType": "polygon",
            "labelerLogin": "gr@datasetninja.com",
            "createdAt": "2023-07-11T11:57:34.893Z",
            "updatedAt": "2023-07-11T11:57:34.893Z",
            "tags": [],
            "classTitle": "b_green",
            "points": {
                "exterior": [
                    [
                        1331,
                        2895
                    ],
                    [
                        1362,
                        2965
                    ],
                    [
                        1357,
                        3024
                    ],
                    [
                        1331,
                        3099
                    ],
                    [
                        1298,
                        3125
                    ],
                    [
                        1261,
                        3141
                    ],
                    [
                        1155,
                        3134
                    ],
                    [
                        1122,
                        3078
                    ],
                    [
                        1110,
                        3038
                    ],
                    [
                        1190,
                        3019
                    ],
                    [
                        1237,
                        2965
                    ],
                    [
                        1265,
                        2871
                    ],
                    [
                        1310,
                        2871
                    ]
                ],
                "interior": []
            }
        }
    ]
}